LICENSE
MANIFEST.in
README.rst
setup.py
django_nonprofit.egg-info/PKG-INFO
django_nonprofit.egg-info/SOURCES.txt
django_nonprofit.egg-info/dependency_links.txt
django_nonprofit.egg-info/requires.txt
django_nonprofit.egg-info/top_level.txt
nonprofit/__init__.py
nonprofit/funding/__init__.py
nonprofit/funding/admin.py
nonprofit/funding/models.py
nonprofit/funding/resources.py
nonprofit/funding/urls.py
nonprofit/funding/views.py
nonprofit/funding/migrations/0001_initial.py
nonprofit/funding/migrations/__init__.py
nonprofit/helpwanted/__init__.py
nonprofit/helpwanted/admin.py
nonprofit/helpwanted/feeds.py
nonprofit/helpwanted/forms.py
nonprofit/helpwanted/models.py
nonprofit/helpwanted/urls.py
nonprofit/helpwanted/views.py
nonprofit/helpwanted/migrations/0001_initial.py
nonprofit/helpwanted/migrations/__init__.py
nonprofit/helpwanted/templates/helpwanted/feeds/description.html
nonprofit/helpwanted/templates/helpwanted/feeds/title.html
nonprofit/mailroom/__init__.py
nonprofit/mailroom/admin.py
nonprofit/mailroom/forms.py
nonprofit/mailroom/models.py
nonprofit/mailroom/resources.py
nonprofit/mailroom/views.py
nonprofit/mailroom/migrations/0001_initial.py
nonprofit/mailroom/migrations/__init__.py
nonprofit/mailroom/templates/mailroom/email.txt
nonprofit/staff/__init__.py
nonprofit/staff/admin.py
nonprofit/staff/models.py
nonprofit/staff/resources.py
nonprofit/staff/migrations/0001_initial.py
nonprofit/staff/migrations/0002_auto__add_field_member_alternate_avatar.py
nonprofit/staff/migrations/__init__.py