Metadata-Version: 1.0
Name: django-nonprofit
Version: 0.4
Summary: Django app for managing and publishing basic information related to a non-profit organization.
Home-page: http://github.com/sunlightlabs/django-nonprofit/
Author: Jeremy Carbaugh
Author-email: jcarbaugh@sunlightfoundation.com
License: BSD
Platform: UNKNOWN
